Metadata-Version: 2.1
Name: mysql2postgresql
Version: 0.4.3
Summary: python-mysql2postgresql
Home-page: UNKNOWN
Author: DewBloodmetal
Author-email: dewscan001@gmail.com
License: UNKNOWN
Keywords: python mysql2postgresql python-mysql2postgresql
Platform: UNKNOWN
Classifier: Development Status :: 2 - Pre-Alpha
Classifier: Programming Language :: Python
Classifier: Programming Language :: Python :: 3
Classifier: Programming Language :: Python :: 3.9
Classifier: Programming Language :: Cython
Classifier: Topic :: Database
